gluoncv/__init__.py
gluoncv/check.py
gluoncv/loss.py
gluoncv/auto/__init__.py
gluoncv/auto/data/__init__.py
gluoncv/auto/data/auto_data.py
gluoncv/auto/data/data_zoo.py
gluoncv/auto/data/dataset.py
gluoncv/auto/estimators/__init__.py
gluoncv/auto/estimators/base_estimator.py
gluoncv/auto/estimators/conf.py
gluoncv/auto/estimators/constants.py
gluoncv/auto/estimators/utils.py
gluoncv/auto/estimators/center_net/__init__.py
gluoncv/auto/estimators/center_net/center_net.py
gluoncv/auto/estimators/center_net/default.py
gluoncv/auto/estimators/faster_rcnn/__init__.py
gluoncv/auto/estimators/faster_rcnn/default.py
gluoncv/auto/estimators/faster_rcnn/faster_rcnn.py
gluoncv/auto/estimators/faster_rcnn/utils.py
gluoncv/auto/estimators/image_classification/__init__.py
gluoncv/auto/estimators/image_classification/default.py
gluoncv/auto/estimators/image_classification/image_classification.py
gluoncv/auto/estimators/image_classification/utils.py
gluoncv/auto/estimators/mask_rcnn/__init__.py
gluoncv/auto/estimators/mask_rcnn/default.py
gluoncv/auto/estimators/mask_rcnn/mask_rcnn.py
gluoncv/auto/estimators/mask_rcnn/utils.py
gluoncv/auto/estimators/ssd/__init__.py
gluoncv/auto/estimators/ssd/default.py
gluoncv/auto/estimators/ssd/ssd.py
gluoncv/auto/estimators/ssd/utils.py
gluoncv/auto/estimators/torch_image_classification/__init__.py
gluoncv/auto/estimators/torch_image_classification/default.py
gluoncv/auto/estimators/torch_image_classification/torch_image_classification.py
gluoncv/auto/estimators/torch_image_classification/utils/__init__.py
gluoncv/auto/estimators/torch_image_classification/utils/constants.py
gluoncv/auto/estimators/torch_image_classification/utils/metrics.py
gluoncv/auto/estimators/torch_image_classification/utils/model.py
gluoncv/auto/estimators/torch_image_classification/utils/optimizer.py
gluoncv/auto/estimators/torch_image_classification/utils/scheduler.py
gluoncv/auto/estimators/torch_image_classification/utils/utils.py
gluoncv-0.10.5.post0.dist-info/LICENSE
gluoncv-0.10.5.post0.dist-info/METADATA
gluoncv-0.10.5.post0.dist-info/WHEEL
gluoncv-0.10.5.post0.dist-info/top_level.txt
gluoncv-0.10.5.post0.dist-info/zip-safe
gluoncv-0.10.5.post0.dist-info/RECORD
