Metadata-Version: 2.1
Name: gluoncv
Version: 0.10.5.post0
Summary: Gluon CV Toolkit
Home-page: https://github.com/dmlc/gluon-cv
Author: Gluon CV Toolkit Contributors
License: Apache-2.0
Platform: UNKNOWN
Requires-Dist: numpy
Requires-Dist: tqdm
Requires-Dist: requests
Requires-Dist: matplotlib
Requires-Dist: portalocker
Requires-Dist: Pillow
Requires-Dist: scipy
Requires-Dist: yacs
Requires-Dist: pandas
Requires-Dist: pyyaml
Requires-Dist: autocfg
Requires-Dist: opencv-python
Provides-Extra: auto
Requires-Dist: autogluon.core ; extra == 'auto'
Provides-Extra: full
Requires-Dist: tensorboardx ; extra == 'full'
Requires-Dist: decord ; extra == 'full'
Requires-Dist: autogluon.core ; extra == 'full'
Requires-Dist: cython ; extra == 'full'
Requires-Dist: pycocotools ; extra == 'full'
